<?xml version="1.0" encoding="utf-8" ?>
<Patch>

<Operation Class="PatchOperationFindMod">
	<mods>
		<li>Erin's Valheim Creatures</li>
	</mods>
	<match Class="PatchOperationSequence">
		<operations>
		
			<li Class="PatchOperationAdd">
				<xpath>Defs/ThingDef[defName="ERN_Scaled_Hide"]/statBases</xpath>
				<value>
					<Textile_Softness>0.2</Textile_Softness>
				</value>
			</li>
		
			<li Class="PatchOperationAdd">
				<xpath>Defs/ThingDef[defName="WoolLox"]/statBases</xpath>
				<value>
					<Textile_Softness>0.52</Textile_Softness>
				</value>
			</li>
				
		</operations>
	</match>
</Operation>

</Patch>